ccdcoe/LICENSE
ccdcoe/__init__.py
ccdcoe/cli.py
ccdcoe/auth/__init__.py
ccdcoe/auth/ldap_client.py
ccdcoe/cicd/__init__.py
ccdcoe/cicd/print_manager.py
ccdcoe/cicd/repo_restrictions.py
ccdcoe/cli_cmds/__init__.py
ccdcoe/cli_cmds/cli_utils/__init__.py
ccdcoe/cli_cmds/cli_utils/mutex.py
ccdcoe/cli_cmds/cli_utils/output.py
ccdcoe/cli_cmds/cli_utils/utils.py
ccdcoe/cli_cmds/deploy_cmds/__init__.py
ccdcoe/cli_cmds/deploy_cmds/commands.py
ccdcoe/cli_cmds/deploy_cmds/general_options/__init__.py
ccdcoe/cli_cmds/deploy_cmds/general_options/options.py
ccdcoe/cli_cmds/deploy_cmds/pipeline_cmds/__init__.py
ccdcoe/cli_cmds/deploy_cmds/pipeline_cmds/commands.py
ccdcoe/cli_cmds/deploy_cmds/pipeline_cmds/schedule_cmds/__init__.py
ccdcoe/cli_cmds/deploy_cmds/pipeline_cmds/schedule_cmds/commands.py
ccdcoe/cli_cmds/gitlab_cmds/__init__.py
ccdcoe/cli_cmds/gitlab_cmds/commands.py
ccdcoe/cli_cmds/gitlab_cmds/projects/__init__.py
ccdcoe/cli_cmds/gitlab_cmds/projects/commands.py
ccdcoe/cli_cmds/gitlab_cmds/projects/namespaces/__init__.py
ccdcoe/cli_cmds/gitlab_cmds/projects/namespaces/commands.py
ccdcoe/cli_cmds/gitlab_cmds/projects/namespaces/pipelines/__init__.py
ccdcoe/cli_cmds/gitlab_cmds/projects/namespaces/pipelines/commands.py
ccdcoe/cli_cmds/gitlab_cmds/projects/namespaces/schedules/__init__.py
ccdcoe/cli_cmds/gitlab_cmds/projects/namespaces/schedules/commands.py
ccdcoe/cli_cmds/gitlab_cmds/user/__init__.py
ccdcoe/cli_cmds/gitlab_cmds/user/commands.py
ccdcoe/cli_cmds/objects/__init__.py
ccdcoe/cli_cmds/objects/namespaces.py
ccdcoe/cli_cmds/pipeline_cmds/__init__.py
ccdcoe/cli_cmds/pipeline_cmds/commands.py
ccdcoe/cli_cmds/providentia_cmds/__init__.py
ccdcoe/cli_cmds/providentia_cmds/commands.py
ccdcoe/clirunner/__init__.py
ccdcoe/clirunner/base.py
ccdcoe/custom_types/__init__.py
ccdcoe/custom_types/sqlalchemy/__init__.py
ccdcoe/custom_types/sqlalchemy/annotations.py
ccdcoe/custom_types/sqlalchemy/custom_types.py
ccdcoe/custom_types/sqlalchemy/model_base.py
ccdcoe-0.0.43.dist-info/licenses/LICENSE
ccdcoe-0.0.43.dist-info/METADATA
ccdcoe-0.0.43.dist-info/WHEEL
ccdcoe-0.0.43.dist-info/entry_points.txt
ccdcoe-0.0.43.dist-info/top_level.txt
ccdcoe-0.0.43.dist-info/RECORD
