Metadata-Version: 2.4
Name: ccdcoe
Version: 0.0.43
Summary: Package with general devops code
Home-page: https://github.com/ccdcoe/ccdcoe
Author: CCDCOE
Author-email: ccdcoe@invalid.com
License: GNU General Public License v3.0
Project-URL: Code, https://github.com/ccdcoe/ccdcoe
Platform: any
Classifier: Development Status :: 5 - Production/Stable
Classifier: License :: OSI Approved :: GNU General Public License v3 or later (GPLv3+)
Classifier: Programming Language :: Python
Classifier: Programming Language :: Python :: 3 :: Only
Classifier: Programming Language :: Python :: 3.10
Classifier: Programming Language :: Python :: 3.11
Classifier: Programming Language :: Python :: 3.12
Classifier: Operating System :: OS Independent
Requires-Python: >=3.10,<4.0
License-File: LICENSE
Requires-Dist: setuptools>=68.1.0
Provides-Extra: cli
Requires-Dist: tabulate<0.10.0,>=0.9.0; extra == "cli"
Requires-Dist: click<9.0.0,>=8.1.8; extra == "cli"
Provides-Extra: flask-plugins
Requires-Dist: flask>=2.3.3; extra == "flask-plugins"
Requires-Dist: sqlalchemy>=2.0.21; extra == "flask-plugins"
Requires-Dist: flask-sqlalchemy>=3.1.1; extra == "flask-plugins"
Requires-Dist: flask-migrate>=4.0.5; extra == "flask-plugins"
Requires-Dist: werkzeug>=2.3.7; extra == "flask-plugins"
Requires-Dist: mysqlclient<3.0.0,>=2.2.7; extra == "flask-plugins"
Provides-Extra: loggers
Requires-Dist: ansicolors>=1.1.8; extra == "loggers"
Provides-Extra: flask-plugins-kafka
Requires-Dist: kafka-python>=2.0.2; extra == "flask-plugins-kafka"
Provides-Extra: flask-middleware
Requires-Dist: rfc3339>=6.2; extra == "flask-middleware"
Provides-Extra: deployments
Requires-Dist: tqdm<5.0.0,>=4.67.1; extra == "deployments"
Provides-Extra: sso
Requires-Dist: authlib>=1.6.4; extra == "sso"
Requires-Dist: flask>=2.3.3; extra == "sso"
Requires-Dist: pyjwt>=2.8.0; extra == "sso"
Provides-Extra: http-apis
Requires-Dist: requests>=2.31.0; extra == "http-apis"
Provides-Extra: cache-redis
Requires-Dist: redis>=5.0.0; extra == "cache-redis"
Provides-Extra: flask-plugins-es
Requires-Dist: eswrap>=0.5.0; extra == "flask-plugins-es"
Requires-Dist: elasticsearch>=8.7.0; extra == "flask-plugins-es"
Provides-Extra: dumpers
Requires-Dist: pyyaml<7.0.0,>=6.0.2; extra == "dumpers"
Provides-Extra: auth
Requires-Dist: python-ldap>=3.4.3; extra == "auth"
Provides-Extra: flask-managers
Requires-Dist: gunicorn>=21.2.0; extra == "flask-managers"
Requires-Dist: flask>=2.3.3; extra == "flask-managers"
Requires-Dist: pyopenssl>=23.2.0; extra == "flask-managers"
Requires-Dist: werkzeug>=2.3.7; extra == "flask-managers"
Requires-Dist: flask-socketio>=5.3.6; extra == "flask-managers"
Provides-Extra: common
Requires-Dist: python-gitlab<7.0.0,>=6.3.0; extra == "common"
Requires-Dist: python-dotenv<2.0.0,>=1.0.1; extra == "common"
Requires-Dist: dataclasses-json<0.7.0,>=0.6.7; extra == "common"
Provides-Extra: gitlab-bot
Requires-Dist: ansicolors>=1.1.8; extra == "gitlab-bot"
Requires-Dist: dataclasses-json<0.7.0,>=0.6.7; extra == "gitlab-bot"
Requires-Dist: python-dotenv<2.0.0,>=1.0.1; extra == "gitlab-bot"
Requires-Dist: redis>=5.0.0; extra == "gitlab-bot"
Requires-Dist: python-gitlab<7.0.0,>=6.3.0; extra == "gitlab-bot"
Provides-Extra: cli-code
Requires-Dist: dataclasses-json<0.7.0,>=0.6.7; extra == "cli-code"
Requires-Dist: python-dotenv<2.0.0,>=1.0.1; extra == "cli-code"
Requires-Dist: tqdm<5.0.0,>=4.67.1; extra == "cli-code"
Requires-Dist: python-gitlab<7.0.0,>=6.3.0; extra == "cli-code"
Requires-Dist: requests>=2.31.0; extra == "cli-code"
Requires-Dist: ansicolors>=1.1.8; extra == "cli-code"
Requires-Dist: pyyaml<7.0.0,>=6.0.2; extra == "cli-code"
Requires-Dist: tabulate<0.10.0,>=0.9.0; extra == "cli-code"
Requires-Dist: click<9.0.0,>=8.1.8; extra == "cli-code"
Provides-Extra: deployment-code
Requires-Dist: ansicolors>=1.1.8; extra == "deployment-code"
Requires-Dist: dataclasses-json<0.7.0,>=0.6.7; extra == "deployment-code"
Requires-Dist: python-dotenv<2.0.0,>=1.0.1; extra == "deployment-code"
Requires-Dist: requests>=2.31.0; extra == "deployment-code"
Requires-Dist: python-gitlab<7.0.0,>=6.3.0; extra == "deployment-code"
Requires-Dist: tqdm<5.0.0,>=4.67.1; extra == "deployment-code"
Provides-Extra: web-flask
Requires-Dist: gunicorn>=21.2.0; extra == "web-flask"
Requires-Dist: sqlalchemy>=2.0.21; extra == "web-flask"
Requires-Dist: python-ldap>=3.4.3; extra == "web-flask"
Requires-Dist: pyjwt>=2.8.0; extra == "web-flask"
Requires-Dist: authlib>=1.6.4; extra == "web-flask"
Requires-Dist: flask-socketio>=5.3.6; extra == "web-flask"
Requires-Dist: flask-migrate>=4.0.5; extra == "web-flask"
Requires-Dist: mysqlclient<3.0.0,>=2.2.7; extra == "web-flask"
Requires-Dist: flask-sqlalchemy>=3.1.1; extra == "web-flask"
Requires-Dist: werkzeug>=2.3.7; extra == "web-flask"
Requires-Dist: dataclasses-json<0.7.0,>=0.6.7; extra == "web-flask"
Requires-Dist: python-dotenv<2.0.0,>=1.0.1; extra == "web-flask"
Requires-Dist: redis>=5.0.0; extra == "web-flask"
Requires-Dist: pyopenssl>=23.2.0; extra == "web-flask"
Requires-Dist: python-gitlab<7.0.0,>=6.3.0; extra == "web-flask"
Requires-Dist: ansicolors>=1.1.8; extra == "web-flask"
Requires-Dist: flask>=2.3.3; extra == "web-flask"
Requires-Dist: rfc3339>=6.2; extra == "web-flask"
Requires-Dist: tabulate<0.10.0,>=0.9.0; extra == "web-flask"
Requires-Dist: click<9.0.0,>=8.1.8; extra == "web-flask"
Provides-Extra: all
Requires-Dist: requests>=2.31.0; extra == "all"
Requires-Dist: flask-migrate>=4.0.5; extra == "all"
Requires-Dist: flask-sqlalchemy>=3.1.1; extra == "all"
Requires-Dist: redis>=5.0.0; extra == "all"
Requires-Dist: pyopenssl>=23.2.0; extra == "all"
Requires-Dist: eswrap>=0.5.0; extra == "all"
Requires-Dist: python-gitlab<7.0.0,>=6.3.0; extra == "all"
Requires-Dist: flask>=2.3.3; extra == "all"
Requires-Dist: ansicolors>=1.1.8; extra == "all"
Requires-Dist: pyyaml<7.0.0,>=6.0.2; extra == "all"
Requires-Dist: rfc3339>=6.2; extra == "all"
Requires-Dist: tabulate<0.10.0,>=0.9.0; extra == "all"
Requires-Dist: click<9.0.0,>=8.1.8; extra == "all"
Requires-Dist: gunicorn>=21.2.0; extra == "all"
Requires-Dist: elasticsearch>=8.7.0; extra == "all"
Requires-Dist: sqlalchemy>=2.0.21; extra == "all"
Requires-Dist: pyjwt>=2.8.0; extra == "all"
Requires-Dist: python-ldap>=3.4.3; extra == "all"
Requires-Dist: flask-socketio>=5.3.6; extra == "all"
Requires-Dist: mysqlclient<3.0.0,>=2.2.7; extra == "all"
Requires-Dist: werkzeug>=2.3.7; extra == "all"
Requires-Dist: dataclasses-json<0.7.0,>=0.6.7; extra == "all"
Requires-Dist: python-dotenv<2.0.0,>=1.0.1; extra == "all"
Requires-Dist: tqdm<5.0.0,>=4.67.1; extra == "all"
Requires-Dist: kafka-python>=2.0.2; extra == "all"
Requires-Dist: authlib>=1.6.4; extra == "all"
Dynamic: author
Dynamic: author-email
Dynamic: classifier
Dynamic: description
Dynamic: description-content-type
Dynamic: home-page
Dynamic: license
Dynamic: license-file
Dynamic: platform
Dynamic: project-url
Dynamic: provides-extra
Dynamic: requires-dist
Dynamic: requires-python
Dynamic: summary
